Workbook

Sheet 01_Raw_Data
A1: AI Business Analyst — Raw Sales Data
A2: Portfolio dataset: 150+ transactions with intentional text inconsistencies/duplicates for cleaning practice.
A4: Order ID | B4: Order Date | C4: Product | D4: Category | E4: Customer | F4: Region | G4: Channel | H4: Salesperson | I4: Quantity | J4: Unit Price | K4: Revenue | L4: Notes
A5: 1001 | B5: 46080 | C5: Smartphone | D5: Electronics | E5: ABC Electronics | F5: West | G5: Distributor | H5: Kabir | I5: 2 | J5: 30000 | K5: 60000 | L5: Priority
A6: 1002 | B6: 46030 | C6: Smartphone | D6: Electronics | E6: XYZ Retail | F6: North | G6: Distributor | H6: Meera | I6: 1 | J6: 30000 | K6: 30000
A7: 1003 | B7: 46166 | C7: Monitor | D7: Electronics | E7: Tech World | F7: West | G7: Distributor | H7: Rohan | I7: 1 | J7: 15000 | K7: 15000 | L7: Priority
A8: 1004 | B8: 46024 | C8: Desk | D8: Furniture | E8: Tech World | F8: West | G8: Store | H8: Rohan | I8: 3 | J8: 12000 | K8: 36000 | L8: Priority
A9: 1005 | B9: 46109 | C9: Desk | D9: Furniture | E9: Metro Traders | F9: North | G9: Store | H9: Diya | I9: 2 | J9: 12000 | K9: 24000
A10: 1006 | B10: 46177 | C10: Smartphone | D10: Electronics | E10: Prime Retail | F10: South | G10: Online | H10: Kabir | I10: 3 | J10: 30000 | K10: 90000 | L10: Repeat customer
A11: 1007 | B11: 46043 | C11: Laptop | D11: Electronics | E11: Urban Store | F11: East | G11: Distributor | H11: Aarav | I11: 4 | J11: 50000 | K11: 200000
A12: 1008 | B12: 46034 | C12: Keyboard | D12: Electronics | E12: Metro Traders | F12: North | G12: Distributor | H12: Diya | I12: 1 | J12: 2500 | K12: 2500 | L12: Priority
A13: 1009 | B13: 46094 | C13: Keyboard | D13: Electronics | E13: XYZ Retail | F13: North | G13: Online | H13: Aarav | I13: 4 | J13: 2500 | K13: 10000 | L13: Promo
A14: 1010 | B14: 46194 | C14: Office Chair | D14: Furniture | E14: PQR Stores | F14: South | G14: Store | H14: Kabir | I14: 2 | J14: 8000 | K14: 16000 | L14: Repeat customer
A15: 1011 | B15: 46064 | C15: Smartphone | D15: Electronics | E15: PQR Stores | F15: South | G15: Distributor | H15: Isha | I15: 2 | J15: 30000 | K15: 60000 | L15: Promo
A16: 1012 | B16: 46079 | C16: Desk | D16: Furniture | E16: Smart Mart | F16: East | G16: Distributor | H16: Isha | I16: 5 | J16: 12000 | K16: 60000 | L16: Repeat customer
A17: 1013 | B17: 46091 | C17: Laptop | D17: Electronics | E17: Tech World | F17: West | G17: Online | H17: Kabir | I17: 4 | J17: 50000 | K17: 200000
A18: 1014 | B18: 46124 | C18: Monitor | D18: Electronics | E18: Metro Traders | F18: North | G18: Online | H18: Isha | I18: 4 | J18: 15000 | K18: 60000 | L18: Promo
A19: 1015 | B19: 46160 | C19: Headphones | D19: Electronics | E19: Smart Mart | F19: East | G19: Online | H19: Diya | I19: 5 | J19: 3000 | K19: 15000 | L19: Repeat customer
A20: 1016 | B20: 46153 | C20: Desk | D20: Furniture | E20: Prime Retail | F20: South | G20: Store | H20: Diya | I20: 2 | J20: 12000 | K20: 24000 | L20: Promo
A21: 1017 | B21: 46197 | C21: Smartphone | D21: Electronics | E21: ABC Electronics | F21: West | G21: Online | H21: Diya | I21: 2 | J21: 30000 | K21: 60000 | L21: Promo
A22: 1018 | B22: 46158 | C22: Smartphone | D22: Electronics | E22: Prime Retail | F22: South | G22: Store | H22: Rohan | I22: 4 | J22: 30000 | K22: 120000 | L22: Repeat customer
A23: 1019 | B23: 46187 | C23: Laptop | D23: Electronics | E23: XYZ RETAIL | F23: North | G23: Distributor | H23: Rohan | I23: 3 | J23: 50000 | K23: 150000 | L23: Repeat customer
A24: 1020 | B24: 46023 | C24: Smartphone | D24: Electronics | E24: Smart Mart | F24: East | G24: Store | H24: Diya | I24: 4 | J24: 30000 | K24: 120000 | L24: Repeat customer
A25: 1021 | B25: 46178 | C25: Headphones | D25: Electronics | E25: XYZ Retail | F25: North | G25: Distributor | H25: Kabir | I25: 5 | J25: 3000 | K25: 15000 | L25: Priority
A26: 1022 | B26: 46023 | C26: Headphones | D26: Electronics | E26: Metro Traders | F26: North | G26: Online | H26: Rohan | I26: 5 | J26: 3000 | K26: 15000
A27: 1023 | B27: 46101 | C27: Office Chair | D27: Furniture | E27: urban store | F27: East | G27: Online | H27: Aarav | I27: 3 | J27: 8000 | K27: 24000 | L27: Priority
A28: 1024 | B28: 46147 | C28: Laptop | D28: Electronics | E28: Tech World | F28: West | G28: Distributor | H28: Aarav | I28: 1 | J28: 50000 | K28: 50000
A29: 1025 | B29: 46065 | C29: Headphones | D29: Electronics | E29: PQR Stores | F29: South | G29: Distributor | H29: Meera | I29: 5 | J29: 3000 | K29: 15000 | L29: Repeat customer
A30: 1026 | B30: 46102 | C30: Desk | D30: Furniture | E30: Tech World | F30: West | G30: Distributor | H30: Isha | I30: 2 | J30: 12000 | K30: 24000 | L30: Promo
A31: 1027 | B31: 46086 | C31: Office Chair | D31: Furniture | E31: Urban Store | F31: East | G31: Distributor | H31: Meera | I31: 1 | J31: 8000 | K31: 8000 | L31: Priority
A32: 1028 | B32: 46081 | C32: Smartphone | D32: Electronics | E32: Metro Traders | F32: North | G32: Online | H32: Rohan | I32: 5 | J32: 30000 | K32: 150000
A33: 1029 | B33: 46081 | C33: Monitor | D33: Electronics | E33: ABC Electronics | F33: west | G33: Online | H33: Isha | I33: 1 | J33: 15000 | K33: 15000
A34: 1030 | B34: 46094 | C34: Laptop | D34: Electronics | E34: Metro Traders | F34: North | G34: Online | H34: Rohan | I34: 2 | J34: 50000 | K34: 100000 | L34: Promo
A35: 1031 | B35: 46144 | C35: Monitor | D35: Electronics | E35: PQR Stores | F35: South | G35: Distributor | H35: Rohan | I35: 5 | J35: 15000 | K35: 75000 | L35: Priority
A36: 1032 | B36: 46191 | C36: Bookshelf | D36: Furniture | E36: Prime Retail | F36: South | G36: Online | H36: Aarav | I36: 1 | J36: 7000 | K36: 7000 | L36: Promo
A37: 1033 | B37: 46195 | C37: Office Chair | D37: Furniture | E37: Prime Retail | F37: South | G37: Store | H37: Meera | I37: 1 | J37: 8000 | K37: 8000
A38: 1034 | B38: 46086 | C38: Laptop | D38: Electronics | E38: Prime Retail | F38: South | G38: Distributor | H38: Kabir | I38: 1 | J38: 50000 | K38: 50000 | L38: Priority
A39: 1035 | B39: 46094 | C39: Monitor | D39: Electronics | E39: Urban Store | F39: East | G39: Online | H39: Meera | I39: 2 | J39: 15000 | K39: 30000 | L39: Promo
A40: 1036 | B40: 46035 | C40: Monitor | D40: Electronics | E40: XYZ Retail | F40: North | G40: Store | H40: Rohan | I40: 1 | J40: 15000 | K40: 15000
A41: 1037 | B41: 46147 | C41: Laptop | D41: Electronics | E41: XYZ Retail | F41: North | G41: Online | H41: Diya | I41: 4 | J41: 50000 | K41: 200000 | L41: Promo
A42: 1038 | B42: 46023 | C42: Monitor | D42: Electronics | E42: PRIME RETAIL | F42: South | G42: Online | H42: Diya | I42: 4 | J42: 15000 | K42: 60000 | L42: Promo
A43: 1039 | B43: 46192 | C43: Keyboard | D43: Electronics | E43: Urban Store | F43: East | G43: Store | H43: Meera | I43: 5 | J43: 2500 | K43: 12500 | L43: Promo
A44: 1040 | B44: 46171 | C44: Headphones | D44: Electronics | E44: Tech World | F44: West | G44: Store | H44: Diya | I44: 1 | J44: 3000 | K44: 3000
A45: 1041 | B45: 46145 | C45: Laptop | D45: Electronics | E45: Metro Traders | F45: North | G45: Online | H45: Aarav | I45: 5 | J45: 50000 | K45: 250000
A46: 1042 | B46: 46040 | C46: Headphones | D46: Electronics | E46: ABC Electronics | F46: West | G46: Distributor | H46: Aarav | I46: 2 | J46: 3000 | K46: 6000
A47: 1043 | B47: 46086 | C47: Smartphone | D47: Electronics | E47: Tech World | F47: West | G47: Store | H47: Aarav | I47: 5 | J47: 30000 | K47: 150000
A48: 1044 | B48: 46167 | C48: Laptop | D48: Electronics | E48: XYZ Retail | F48: North | G48: Store | H48: Isha | I48: 5 | J48: 50000 | K48: 250000
A49: 1045 | B49: 46084 | C49: Office Chair | D49: Furniture | E49: Smart Mart | F49: East | G49: Online | H49: Isha | I49: 3 | J49: 8000 | K49: 24000 | L49: Repeat customer
A50: 1046 | B50: 46140 | C50: Desk | D50: Furniture | E50: pqr stores | F50: South | G50: Distributor | H50: Isha | I50: 3 | J50: 12000 | K50: 36000 | L50: Repeat customer
A51: 1047 | B51: 46048 | C51: Smartphone | D51: Electronics | E51: ABC Electronics | F51: West | G51: Store | H51: Rohan | I51: 5 | J51: 30000 | K51: 150000
A52: 1048 | B52: 46085 | C52: Monitor | D52: Electronics | E52: Smart Mart | F52: East | G52: Online | H52: Kabir | I52: 1 | J52: 15000 | K52: 15000 | L52: Repeat customer
A53: 1049 | B53: 46179 | C53: Keyboard | D53: Electronics | E53: PQR Stores | F53: South | G53: Store | H53: Rohan | I53: 3 | J53: 2500 | K53: 7500
A54: 1050 | B54: 46090 | C54: Laptop | D54: Electronics | E54: Smart Mart | F54: East | G54: Distributor | H54: Aarav | I54: 2 | J54: 50000 | K54: 100000
A55: 1051 | B55: 46076 | C55: Smartphone | D55: Electronics | E55: PQR Stores | F55: South | G55: Store | H55: Kabir | I55: 5 | J55: 30000 | K55: 150000 | L55: Repeat customer
A56: 1052 | B56: 46036 | C56: Monitor | D56: Electronics | E56: Smart Mart | F56: East | G56: Distributor | H56: Meera | I56: 3 | J56: 15000 | K56: 45000
A57: 1053 | B57: 46056 | C57: Desk | D57: Furniture | E57: Smart Mart | F57: East | G57: Online | H57: Aarav | I57: 3 | J57: 12000 | K57: 36000 | L57: Repeat customer
A58: 1054 | B58: 46166 | C58: Headphones | D58: Electronics | E58: Urban Store | F58: East | G58: Distributor | H58: Isha | I58: 4 | J58: 3000 | K58: 12000
A59: 1055 | B59: 46032 | C59: Smartphone | D59: Electronics | E59: XYZ Retail | F59: North | G59: Distributor | H59: Diya | I59: 5 | J59: 30000 | K59: 150000 | L59: Repeat customer
A60: 1056 | B60: 46116 | C60: Headphones | D60: Electronics | E60: Prime Retail | F60: South | G60: Online | H60: Aarav | I60: 3 | J60: 3000 | K60: 9000
A61: 1057 | B61: 46113 | C61: Office Chair | D61: Furniture | E61: TECH WORLD | F61: West | G61: Distributor | H61: Diya | I61: 1 | J61: 8000 | K61: 8000
A62: 1058 | B62: 46128 | C62: Desk | D62: Furniture | E62: PQR Stores | F62: south | G62: Online | H62: Diya | I62: 2 | J62: 12000 | K62: 24000
A63: 1059 | B63: 46091 | C63: Headphones | D63: Electronics | E63: Metro Traders | F63: North | G63: Store | H63: Isha | I63: 2 | J63: 3000 | K63: 6000 | L63: Priority
A64: 1060 | B64: 46074 | C64: Smartphone | D64: Electronics | E64: Prime Retail | F64: South | G64: Online | H64: Meera | I64: 2 | J64: 30000 | K64: 60000 | L64: Promo
A65: 1061 | B65: 46191 | C65: Office Chair | D65: Furniture | E65: Smart Mart | F65: East | G65: Online | H65: Diya | I65: 1 | J65: 8000 | K65: 8000 | L65: Priority
A66: 1062 | B66: 46112 | C66: Desk | D66: Furniture | E66: Metro Traders | F66: North | G66: Store | H66: Aarav | I66: 3 | J66: 12000 | K66: 36000
A67: 1063 | B67: 46068 | C67: Desk | D67: Furniture | E67: Metro Traders | F67: North | G67: Online | H67: Aarav | I67: 3 | J67: 12000 | K67: 36000
A68: 1064 | B68: 46111 | C68: Keyboard | D68: Electronics | E68: ABC Electronics | F68: West | G68: Online | H68: Rohan | I68: 4 | J68: 2500 | K68: 10000 | L68: Repeat customer
A69: 1065 | B69: 46088 | C69: Desk | D69: Furniture | E69: XYZ Retail | F69: North | G69: Store | H69: Rohan | I69: 2 | J69: 12000 | K69: 24000
A70: 1066 | B70: 46116 | C70: Desk | D70: Furniture | E70: ABC Electronics | F70: West | G70: Distributor | H70: Rohan | I70: 2 | J70: 12000 | K70: 24000 | L70: Promo
A71: 1067 | B71: 46099 | C71: Smartphone | D71: Electronics | E71: Metro Traders | F71: North | G71: Distributor | H71: Kabir | I71: 1 | J71: 30000 | K71: 30000
A72: 1068 | B72: 46164 | C72: Keyboard | D72: Electronics | E72: Prime Retail | F72: South | G72: Store | H72: Meera | I72: 3 | J72: 2500 | K72: 7500 | L72: Priority
A73: 1069 | B73: 46180 | C73: Monitor | D73: Electronics | E73: prime retail | F73: South | G73: Distributor | H73: Meera | I73: 2 | J73: 15000 | K73: 30000
A74: 1070 | B74: 46096 | C74: Keyboard | D74: Electronics | E74: Prime Retail | F74: South | G74: Distributor | H74: Aarav | I74: 3 | J74: 2500 | K74: 7500 | L74: Priority
A75: 1071 | B75: 46195 | C75: Desk | D75: Furniture | E75: Metro Traders | F75: North | G75: Store | H75: Meera | I75: 4 | J75: 12000 | K75: 48000 | L75: Priority
A76: 1072 | B76: 46154 | C76: Bookshelf | D76: Furniture | E76: PQR Stores | F76: South | G76: Distributor | H76: Aarav | I76: 3 | J76: 7000 | K76: 21000
A77: 1073 | B77: 46080 | C77: Office Chair | D77: Furniture | E77: XYZ Retail | F77: North | G77: Online | H77: Isha | I77: 3 | J77: 8000 | K77: 24000 | L77: Priority
A78: 1074 | B78: 46179 | C78: Headphones | D78: Electronics | E78: ABC Electronics | F78: West | G78: Online | H78: Diya | I78: 4 | J78: 3000 | K78: 12000
A79: 1075 | B79: 46201 | C79: Bookshelf | D79: Furniture | E79: Prime Retail | F79: South | G79: Distributor | H79: Rohan | I79: 2 | J79: 7000 | K79: 14000 | L79: Promo
A80: 1076 | B80: 46050 | C80: Bookshelf | D80: Furniture | E80: PRIME RETAIL | F80: South | G80: Online | H80: Diya | I80: 1 | J80: 7000 | K80: 7000 | L80: Promo
A81: 1077 | B81: 46035 | C81: Monitor | D81: Electronics | E81: PQR Stores | F81: South | G81: Distributor | H81: Rohan | I81: 4 | J81: 15000 | K81: 60000
A82: 1078 | B82: 46193 | C82: Monitor | D82: Electronics | E82: XYZ Retail | F82: North | G82: Store | H82: Diya | I82: 4 | J82: 15000 | K82: 60000
A83: 1079 | B83: 46132 | C83: Office Chair | D83: Furniture | E83: Urban Store | F83: East | G83: Distributor | H83: Isha | I83: 5 | J83: 8000 | K83: 40000
A84: 1080 | B84: 46089 | C84: Bookshelf | D84: Furniture | E84: PQR Stores | F84: South | G84: Distributor | H84: Meera | I84: 4 | J84: 7000 | K84: 28000 | L84: Priority
A85: 1081 | B85: 46135 | C85: Keyboard | D85: Electronics | E85: Urban Store | F85: East | G85: Distributor | H85: Diya | I85: 3 | J85: 2500 | K85: 7500
A86: 1082 | B86: 46161 | C86: Keyboard | D86: Electronics | E86: Tech World | F86: West | G86: Store | H86: Kabir | I86: 3 | J86: 2500 | K86: 7500
A87: 1083 | B87: 46203 | C87: Headphones | D87: Electronics | E87: PQR Stores | F87: South | G87: Online | H87: Meera | I87: 2 | J87: 3000 | K87: 6000 | L87: Priority
A88: 1084 | B88: 46142 | C88: Smartphone | D88: Electronics | E88: Prime Retail | F88: South | G88: Store | H88: Kabir | I88: 5 | J88: 30000 | K88: 150000 | L88: Promo
A89: 1085 | B89: 46201 | C89: Laptop | D89: Electronics | E89: Tech World | F89: West | G89: Store | H89: Meera | I89: 5 | J89: 50000 | K89: 250000
A90: 1086 | B90: 46122 | C90: Desk | D90: Furniture | E90: Urban Store | F90: East | G90: Online | H90: Kabir | I90: 3 | J90: 12000 | K90: 36000 | L90: Promo
A91: 1087 | B91: 46147 | C91: Monitor | D91: Electronics | E91: Urban Store | F91: east | G91: Online | H91: Kabir | I91: 4 | J91: 15000 | K91: 60000
A92: 1088 | B92: 46065 | C92: Desk | D92: Furniture | E92: Metro Traders | F92: North | G92: Distributor | H92: Isha | I92: 4 | J92: 12000 | K92: 48000 | L92: Promo
A93: 1089 | B93: 46192 | C93: Headphones | D93: Electronics | E93: ABC Electronics | F93: West | G93: Store | H93: Rohan | I93: 5 | J93: 3000 | K93: 15000
A94: 1090 | B94: 46035 | C94: Smartphone | D94: Electronics | E94: Prime Retail | F94: South | G94: Online | H94: Meera | I94: 2 | J94: 30000 | K94: 60000 | L94: Repeat customer
A95: 1091 | B95: 46109 | C95: Desk | D95: Furniture | E95: Metro Traders | F95: North | G95: Online | H95: Meera | I95: 3 | J95: 12000 | K95: 36000 | L95: Promo
A96: 1092 | B96: 46027 | C96: Keyboard | D96: Electronics | E96: prime retail | F96: South | G96: Store | H96: Aarav | I96: 4 | J96: 2500 | K96: 10000
A97: 1093 | B97: 46189 | C97: Laptop | D97: Electronics | E97: Metro Traders | F97: North | G97: Online | H97: Isha | I97: 1 | J97: 50000 | K97: 50000
A98: 1094 | B98: 46062 | C98: Laptop | D98: Electronics | E98: Tech World | F98: West | G98: Online | H98: Aarav | I98: 5 | J98: 50000 | K98: 250000 | L98: Priority
A99: 1095 | B99: 46078 | C99: Headphones | D99: Electronics | E99: URBAN STORE | F99: East | G99: Distributor | H99: Aarav | I99: 5 | J99: 3000 | K99: 15000 | L99: Promo
A100: 1096 | B100: 46052 | C100: Keyboard | D100: Electronics | E100: Metro Traders | F100: North | G100: Online | H100: Rohan | I100: 5 | J100: 2500 | K100: 12500 | L100: Priority
A101: 1097 | B101: 46170 | C101: Keyboard | D101: Electronics | E101: XYZ Retail | F101: North | G101: Distributor | H101: Aarav | I101: 3 | J101: 2500 | K101: 7500 | L101: Promo
...

Sheet 00_Instructions
A1: AI Business Analyst — Excel Portfolio Workbook
A2: A practical Excel project designed to demonstrate analyst skills, not just a pretty dashboard.
A4: Step | B4: Sheet | C4: What to do
A5: 1 | B5: Start with 01_Raw_Data | C5: Review the raw transactions, filters, table structure and intentional data-quality issues.
A6: 2 | B6: Open 02_Clean_Data | C6: See formula-driven cleaning and calculated columns.
A7: 3 | B7: Study 03_Lookups | C7: Understand XLOOKUP and INDEX-MATCH reference logic.
A8: 4 | B8: Practice 04_Formula_Analysis | C8: Use the formulas as interview examples.
A9: 5 | B9: Review 05_Pivot_Style | C9: Explain how grouped summaries answer business questions.
A10: 6 | B10: Use 07_Interactive_Analysis | C10: Change dropdowns and observe SUMIFS / COUNTIFS results.
A11: 7 | B11: Present 08_Executive_Dashboard | C11: Use this page as the management-facing output.
A12: 8 | B12: Use 10_Excel_Skills | C12: Use it as your interview revision checklist.

Sheet 02_Clean_Data
A1: Data Cleaning & Calculated Columns
A2: Formula-driven cleaning: TRIM, PROPER, IFERROR, date extraction, revenue checks, profit and margin calculations.
A4: Order ID | B4: Order Date | C4: Product | D4: Category | E4: Customer | F4: Region | G4: Channel | H4: Salesperson | I4: Quantity | J4: Unit Price | K4: Revenue | L4: Year | M4: Month | N4: Clean Customer | O4: Clean Product | P4: Profit | Q4: Profit Margin | R4: Revenue Band
A5: ='01_Raw_Data'!A5 | B5: ='01_Raw_Data'!B5 | C5: =PROPER(TRIM('01_Raw_Data'!C5)) | D5: =PROPER(TRIM('01_Raw_Data'!D5)) | E5: =PROPER(TRIM('01_Raw_Data'!E5)) | F5: =PROPER(TRIM('01_Raw_Data'!F5)) | G5: =PROPER(TRIM('01_Raw_Data'!G5)) | H5: =PROPER(TRIM('01_Raw_Data'!H5)) | I5: ='01_Raw_Data'!I5 | J5: ='01_Raw_Data'!J5 | K5: =IFERROR(I5*J5,0) | L5: =YEAR(B5) | M5: =TEXT(B5,"mmm") | N5: =PROPER(TRIM(E5)) | O5: =PROPER(TRIM(C5)) | P5: =K5*IFERROR(XLOOKUP(D5,'03_Lookups'!$E$5:$E$6,'03_Lookups'!$F$5:$F$6),0) | Q5: =IFERROR(P5/K5,0) | R5: =IFS(K5>=50000,"High",K5>=20000,"Medium",TRUE,"Low")
A6: ='01_Raw_Data'!A6 | B6: ='01_Raw_Data'!B6 | C6: =PROPER(TRIM('01_Raw_Data'!C6)) | D6: =PROPER(TRIM('01_Raw_Data'!D6)) | E6: =PROPER(TRIM('01_Raw_Data'!E6)) | F6: =PROPER(TRIM('01_Raw_Data'!F6)) | G6: =PROPER(TRIM('01_Raw_Data'!G6)) | H6: =PROPER(TRIM('01_Raw_Data'!H6)) | I6: ='01_Raw_Data'!I6 | J6: ='01_Raw_Data'!J6 | K6: =IFERROR(I6*J6,0) | L6: =YEAR(B6) | M6: =TEXT(B6,"mmm") | N6: =PROPER(TRIM(E6)) | O6: =PROPER(TRIM(C6)) | P6: =K6*IFERROR(XLOOKUP(D6,'03_Lookups'!$E$5:$E$6,'03_Lookups'!$F$5:$F$6),0) | Q6: =IFERROR(P6/K6,0) | R6: =IFS(K6>=50000,"High",K6>=20000,"Medium",TRUE,"Low")
A7: ='01_Raw_Data'!A7 | B7: ='01_Raw_Data'!B7 | C7: =PROPER(TRIM('01_Raw_Data'!C7)) | D7: =PROPER(TRIM('01_Raw_Data'!D7)) | E7: =PROPER(TRIM('01_Raw_Data'!E7)) | F7: =PROPER(TRIM('01_Raw_Data'!F7)) | G7: =PROPER(TRIM('01_Raw_Data'!G7)) | H7: =PROPER(TRIM('01_Raw_Data'!H7)) | I7: ='01_Raw_Data'!I7 | J7: ='01_Raw_Data'!J7 | K7: =IFERROR(I7*J7,0) | L7: =YEAR(B7) | M7: =TEXT(B7,"mmm") | N7: =PROPER(TRIM(E7)) | O7: =PROPER(TRIM(C7)) | P7: =K7*IFERROR(XLOOKUP(D7,'03_Lookups'!$E$5:$E$6,'03_Lookups'!$F$5:$F$6),0) | Q7: =IFERROR(P7/K7,0) | R7: =IFS(K7>=50000,"High",K7>=20000,"Medium",TRUE,"Low")
A8: ='01_Raw_Data'!A8 | B8: ='01_Raw_Data'!B8 | C8: =PROPER(TRIM('01_Raw_Data'!C8)) | D8: =PROPER(TRIM('01_Raw_Data'!D8)) | E8: =PROPER(TRIM('01_Raw_Data'!E8)) | F8: =PROPER(TRIM('01_Raw_Data'!F8)) | G8: =PROPER(TRIM('01_Raw_Data'!G8)) | H8: =PROPER(TRIM('01_Raw_Data'!H8)) | I8: ='01_Raw_Data'!I8 | J8: ='01_Raw_Data'!J8 | K8: =IFERROR(I8*J8,0) | L8: =YEAR(B8) | M8: =TEXT(B8,"mmm") | N8: =PROPER(TRIM(E8)) | O8: =PROPER(TRIM(C8)) | P8: =K8*IFERROR(XLOOKUP(D8,'03_Lookups'!$E$5:$E$6,'03_Lookups'!$F$5:$F$6),0) | Q8: =IFERROR(P8/K8,0) | R8: =IFS(K8>=50000,"High",K8>=20000,"Medium",TRUE,"Low")
A9: ='01_Raw_Data'!A9 | B9: ='01_Raw_Data'!B9 | C9: =PROPER(TRIM('01_Raw_Data'!C9)) | D9: =PROPER(TRIM('01_Raw_Data'!D9)) | E9: =PROPER(TRIM('01_Raw_Data'!E9)) | F9: =PROPER(TRIM('01_Raw_Data'!F9)) | G9: =PROPER(TRIM('01_Raw_Data'!G9)) | H9: =PROPER(TRIM('01_Raw_Data'!H9)) | I9: ='01_Raw_Data'!I9 | J9: ='01_Raw_Data'!J9 | K9: =IFERROR(I9*J9,0) | L9: =YEAR(B9) | M9: =TEXT(B9,"mmm") | N9: =PROPER(TRIM(E9)) | O9: =PROPER(TRIM(C9)) | P9: =K9*IFERROR(XLOOKUP(D9,'03_Lookups'!$E$5:$E$6,'03_Lookups'!$F$5:$F$6),0) | Q9: =IFERROR(P9/K9,0) | R9: =IFS(K9>=50000,"High",K9>=20000,"Medium",TRUE,"Low")
A10: ='01_Raw_Data'!A10 | B10: ='01_Raw_Data'!B10 | C10: =PROPER(TRIM('01_Raw_Data'!C10)) | D10: =PROPER(TRIM('01_Raw_Data'!D10)) | E10: =PROPER(TRIM('01_Raw_Data'!E10)) | F10: =PROPER(TRIM('01_Raw_Data'!F10)) | G10: =PROPER(TRIM('01_Raw_Data'!G10)) | H10: =PROPER(TRIM('01_Raw_Data'!H10)) | I10: ='01_Raw_Data'!I10 | J10: ='01_Raw_Data'!J10 | K10: =IFERROR(I10*J10,0) | L10: =YEAR(B10) | M10: =TEXT(B10,"mmm") | N10: =PROPER(TRIM(E10)) | O10: =PROPER(TRIM(C10)) | P10: =K10*IFERROR(XLOOKUP(D10,'03_Lookups'!$E$5:$E$6,'03_Lookups'!$F$5:$F$6),0) | Q10: =IFERROR(P10/K10,0) | R10: =IFS(K10>=50000,"High",K10>=20000,"Medium",TRUE,"Low")
A11: ='01_Raw_Data'!A11 | B11: ='01_Raw_Data'!B11 | C11: =PROPER(TRIM('01_Raw_Data'!C11)) | D11: =PROPER(TRIM('01_Raw_Data'!D11)) | E11: =PROPER(TRIM('01_Raw_Data'!E11)) | F11: =PROPER(TRIM('01_Raw_Data'!F11)) | G11: =PROPER(TRIM('01_Raw_Data'!G11)) | H11: =PROPER(TRIM('01_Raw_Data'!H11)) | I11: ='01_Raw_Data'!I11 | J11: ='01_Raw_Data'!J11 | K11: =IFERROR(I11*J11,0) | L11: =YEAR(B11) | M11: =TEXT(B11,"mmm") | N11: =PROPER(TRIM(E11)) | O11: =PROPER(TRIM(C11)) | P11: =K11*IFERROR(XLOOKUP(D11,'03_Lookups'!$E$5:$E$6,'03_Lookups'!$F$5:$F$6),0) | Q11: =IFERROR(P11/K11,0) | R11: =IFS(K11>=50000,"High",K11>=20000,"Medium",TRUE,"Low")
A12: ='01_Raw_Data'!A12 | B12: ='01_Raw_Data'!B12 | C12: =PROPER(TRIM('01_Raw_Data'!C12)) | D12: =PROPER(TRIM('01_Raw_Data'!D12)) | E12: =PROPER(TRIM('01_Raw_Data'!E12)) | F12: =PROPER(TRIM('01_Raw_Data'!F12)) | G12: =PROPER(TRIM('01_Raw_Data'!G12)) | H12: =PROPER(TRIM('01_Raw_Data'!H12)) | I12: ='01_Raw_Data'!I12 | J12: ='01_Raw_Data'!J12 | K12: =IFERROR(I12*J12,0) | L12: =YEAR(B12) | M12: =TEXT(B12,"mmm") | N12: =PROPER(TRIM(E12)) | O12: =PROPER(TRIM(C12)) | P12: =K12*IFERROR(XLOOKUP(D12,'03_Lookups'!$E$5:$E$6,'03_Lookups'!$F$5:$F$6),0) | Q12: =IFERROR(P12/K12,0) | R12: =IFS(K12>=50000,"High",K12>=20000,"Medium",TRUE,"Low")
A13: ='01_Raw_Data'!A13 | B13: ='01_Raw_Data'!B13 | C13: =PROPER(TRIM('01_Raw_Data'!C13)) | D13: =PROPER(TRIM('01_Raw_Data'!D13)) | E13: =PROPER(TRIM('01_Raw_Data'!E13)) | F13: =PROPER(TRIM('01_Raw_Data'!F13)) | G13: =PROPER(TRIM('01_Raw_Data'!G13)) | H13: =PROPER(TRIM('01_Raw_Data'!H13)) | I13: ='01_Raw_Data'!I13 | J13: ='01_Raw_Data'!J13 | K13: =IFERROR(I13*J13,0) | L13: =YEAR(B13) | M13: =TEXT(B13,"mmm") | N13: =PROPER(TRIM(E13)) | O13: =PROPER(TRIM(C13)) | P13: =K13*IFERROR(XLOOKUP(D13,'03_Lookups'!$E$5:$E$6,'03_Lookups'!$F$5:$F$6),0) | Q13: =IFERROR(P13/K13,0) | R13: =IFS(K13>=50000,"High",K13>=20000,"Medium",TRUE,"Low")
A14: ='01_Raw_Data'!A14 | B14: ='01_Raw_Data'!B14 | C14: =PROPER(TRIM('01_Raw_Data'!C14)) | D14: =PROPER(TRIM('01_Raw_Data'!D14)) | E14: =PROPER(TRIM('01_Raw_Data'!E14)) | F14: =PROPER(TRIM('01_Raw_Data'!F14)) | G14: =PROPER(TRIM('01_Raw_Data'!G14)) | H14: =PROPER(TRIM('01_Raw_Data'!H14)) | I14: ='01_Raw_Data'!I14 | J14: ='01_Raw_Data'!J14 | K14: =IFERROR(I14*J14,0) | L14: =YEAR(B14) | M14: =TEXT(B14,"mmm") | N14: =PROPER(TRIM(E14)) | O14: =PROPER(TRIM(C14)) | P14: =K14*IFERROR(XLOOKUP(D14,'03_Lookups'!$E$5:$E$6,'03_Lookups'!$F$5:$F$6),0) | Q14: =IFERROR(P14/K14,0) | R14: =IFS(K14>=50000,"High",K14>=20000,"Medium",TRUE,"Low")
A15: ='01_Raw_Data'!A15 | B15: ='01_Raw_Data'!B15 | C15: =PROPER(TRIM('01_Raw_Data'!C15)) | D15: =PROPER(TRIM('01_Raw_Data'!D15)) | E15: =PROPER(TRIM('01_Raw_Data'!E15)) | F15: =PROPER(TRIM('01_Raw_Data'!F15)) | G15: =PROPER(TRIM('01_Raw_Data'!G15)) | H15: =PROPER(TRIM('01_Raw_Data'!H15)) | I15: ='01_Raw_Data'!I15 | J15: ='01_Raw_Data'!J15 | K15: =IFERROR(I15*J15,0) | L15: =YEAR(B15) | M15: =TEXT(B15,"mmm") | N15: =PROPER(TRIM(E15)) | O15: =PROPER(TRIM(C15)) | P15: =K15*IFERROR(XLOOKUP(D15,'03_Lookups'!$E$5:$E$6,'03_Lookups'!$F$5:$F$6),0) | Q15: =IFERROR(P15/K15,0) | R15: =IFS(K15>=50000,"High",K15>=20000,"Medium",TRUE,"Low")
A16: ='01_Raw_Data'!A16 | B16: ='01_Raw_Data'!B16 | C16: =PROPER(TRIM('01_Raw_Data'!C16)) | D16: =PROPER(TRIM('01_Raw_Data'!D16)) | E16: =PROPER(TRIM('01_Raw_Data'!E16)) | F16: =PROPER(TRIM('01_Raw_Data'!F16)) | G16: =PROPER(TRIM('01_Raw_Data'!G16)) | H16: =PROPER(TRIM('01_Raw_Data'!H16)) | I16: ='01_Raw_Data'!I16 | J16: ='01_Raw_Data'!J16 | K16: =IFERROR(I16*J16,0) | L16: =YEAR(B16) | M16: =TEXT(B16,"mmm") | N16: =PROPER(TRIM(E16)) | O16: =PROPER(TRIM(C16)) | P16: =K16*IFERROR(XLOOKUP(D16,'03_Lookups'!$E$5:$E$6,'03_Lookups'!$F$5:$F$6),0) | Q16: =IFERROR(P16/K16,0) | R16: =IFS(K16>=50000,"High",K16>=20000,"Medium",TRUE,"Low")
... A157: ='01_Raw_Data'!A157 | B157: ='01_Raw_Data'!B157 | C157: =PROPER(TRIM('01_Raw_Data'!C157)) | D157: =PROPER(TRIM('01_Raw_Data'!D157)) | E157: =PROPER(TRIM('01_Raw_Data'!E157)) | F157: =PROPER(TRIM('01_Raw_Data'!F157)) | G157: =PROPER(TRIM('01_Raw_Data'!G157)) | H157: =PROPER(TRIM('01_Raw_Data'!H157)) | I157: ='01_Raw_Data'!I157 | J157: ='01_Raw_Data'!J157 | K157: =IFERROR(I157*J157,0) | L157: =YEAR(B157) | M157: =TEXT(B157,"mmm") | N157: =PROPER(TRIM(E157)) | O157: =PROPER(TRIM(C157)) | P157: =K157*IFERROR(XLOOKUP(D157,'03_Lookups'!$E$5:$E$6,'03_Lookups'!$F$5:$F$6),0) | Q157: =IFERROR(P157/K157,0) | R157: =IFS(K157>=50000,"High",K157>=20000,"Medium",TRUE,"Low")

Sheet 03_Lookups
A1: Lookup Tables & Reference Data
A2: Demonstrates XLOOKUP / INDEX-MATCH style reference tables and controlled input lists.
A4: Category | B4: Margin Assumption | D4: Product | E4: Category | F4: Margin Assumption | H4: Region List
A5: Electronics | B5: 0.18 | D5: Laptop | E5: Electronics | F5: 0.18 | H5: North
A6: Furniture | B6: 0.2 | D6: Smartphone | E6: Electronics | F6: 0.15 | H6: South
D7: Headphones | E7: Electronics | F7: 0.25 | H7: East
D8: Monitor | E8: Electronics | F8: 0.2 | H8: West
A9: Example XLOOKUP | B9: =XLOOKUP("Laptop",D5:D12,F5:F12) | D9: Keyboard | E9: Electronics | F9: 0.28
A10: Example INDEX-MATCH | B10: =INDEX(E5:E12,MATCH("Desk",D5:D12,0)) | D10: Office Chair | E10: Furniture | F10: 0.22
A11: Example IFERROR | B11: =IFERROR(XLOOKUP("Unknown",D5:D12,F5:F12),"Not Found") | D11: Desk | E11: Furniture | F11: 0.2
D12: Bookshelf | E12: Furniture | F12: 0.19

Sheet 04_Formula_Analysis
A1: Formula-Based Business Analysis
A2: Interview-ready examples using SUM, AVERAGE, COUNTIF(S), SUMIF(S), AVERAGEIF(S), ranking and dynamic selectors.
A4: Metric | B4: Formula / Result
A5: Total Revenue | B5: =SUM('02_Clean_Data'!K5:K157)
A6: Average Order Value | B6: =AVERAGE('02_Clean_Data'!K5:K157)
A7: Total Orders | B7: =COUNTA('02_Clean_Data'!A5:A157)
A8: Electronics Revenue | B8: =SUMIF('02_Clean_Data'!D5:D157,"Electronics",'02_Clean_Data'!K5:K157)
A9: Furniture Revenue | B9: =SUMIF('02_Clean_Data'!D5:D157,"Furniture",'02_Clean_Data'!K5:K157)
A10: West Revenue | B10: =SUMIF('02_Clean_Data'!F5:F157,"West",'02_Clean_Data'!K5:K157)
A11: Online Orders | B11: =COUNTIF('02_Clean_Data'!G5:G157,"Online")
A12: Electronics + Online Revenue | B12: =SUMIFS('02_Clean_Data'!K5:K157,'02_Clean_Data'!D5:D157,"Electronics",'02_Clean_Data'!G5:G157,"Online")
A13: High Revenue Transactions | B13: =COUNTIF('02_Clean_Data'!R5:R157,"High")
A14: Average Electronics Revenue | B14: =AVERAGEIF('02_Clean_Data'!D5:D157,"Electronics",'02_Clean_Data'!K5:K157)
A17: Key Excel Skills
A18: SUM / AVERAGE | B18: Used in this workbook
A19: SUMIF / COUNTIF | B19: Used in this workbook
A20: SUMIFS / COUNTIFS | B20: Used in this workbook
A21: AVERAGEIF(S) | B21: Used in this workbook
A22: IF / IFS / IFERROR | B22: Used in this workbook
A23: Text cleaning | B23: Used in this workbook
A24: Date functions | B24: Used in this workbook
A25: Lookup functions | B25: Used in this workbook

Sheet 05_Pivot_Style
A1: Pivot-Style Analysis
A2: Formula-built summaries that mimic common PivotTable outputs. Use these to explain trends in interviews.
A4: Product | B4: Revenue | C4: Orders | D4: Avg Revenue | E4: Rank | G4: Category | H4: Revenue | I4: Orders | J4: Avg Order Value
A5: Laptop | B5: =SUMIF('02_Clean_Data'!O5:O157,A5,'02_Clean_Data'!K5:K157) | C5: =COUNTIF('02_Clean_Data'!O5:O157,A5) | D5: =IFERROR(B5/C5,0) | E5: =RANK(B5,$B$5:$B$12,0) | G5: Electronics | H5: =SUMIF('02_Clean_Data'!D5:D157,G5,'02_Clean_Data'!K5:K157) | I5: =COUNTIF('02_Clean_Data'!D5:D157,G5) | J5: =IFERROR(H5/I5,0)
A6: Smartphone | B6: =SUMIF('02_Clean_Data'!O5:O157,A6,'02_Clean_Data'!K5:K157) | C6: =COUNTIF('02_Clean_Data'!O5:O157,A6) | D6: =IFERROR(B6/C6,0) | E6: =RANK(B6,$B$5:$B$12,0) | G6: Furniture | H6: =SUMIF('02_Clean_Data'!D5:D157,G6,'02_Clean_Data'!K5:K157) | I6: =COUNTIF('02_Clean_Data'!D5:D157,G6) | J6: =IFERROR(H6/I6,0)
A7: Headphones | B7: =SUMIF('02_Clean_Data'!O5:O157,A7,'02_Clean_Data'!K5:K157) | C7: =COUNTIF('02_Clean_Data'!O5:O157,A7) | D7: =IFERROR(B7/C7,0) | E7: =RANK(B7,$B$5:$B$12,0)
A8: Monitor | B8: =SUMIF('02_Clean_Data'!O5:O157,A8,'02_Clean_Data'!K5:K157) | C8: =COUNTIF('02_Clean_Data'!O5:O157,A8) | D8: =IFERROR(B8/C8,0) | E8: =RANK(B8,$B$5:$B$12,0)
A9: Keyboard | B9: =SUMIF('02_Clean_Data'!O5:O157,A9,'02_Clean_Data'!K5:K157) | C9: =COUNTIF('02_Clean_Data'!O5:O157,A9) | D9: =IFERROR(B9/C9,0) | E9: =RANK(B9,$B$5:$B$12,0)
A10: Office Chair | B10: =SUMIF('02_Clean_Data'!O5:O157,A10,'02_Clean_Data'!K5:K157) | C10: =COUNTIF('02_Clean_Data'!O5:O157,A10) | D10: =IFERROR(B10/C10,0) | E10: =RANK(B10,$B$5:$B$12,0)
A11: Desk | B11: =SUMIF('02_Clean_Data'!O5:O157,A11,'02_Clean_Data'!K5:K157) | C11: =COUNTIF('02_Clean_Data'!O5:O157,A11) | D11: =IFERROR(B11/C11,0) | E11: =RANK(B11,$B$5:$B$12,0)
A12: Bookshelf | B12: =SUMIF('02_Clean_Data'!O5:O157,A12,'02_Clean_Data'!K5:K157) | C12: =COUNTIF('02_Clean_Data'!O5:O157,A12) | D12: =IFERROR(B12/C12,0) | E12: =RANK(B12,$B$5:$B$12,0)

Sheet 06_Monthly_Analysis
A1: Monthly Trend Analysis
A2: Monthly revenue, order count and average order value using SUMIFS / COUNTIFS.
A4: Month | B4: Revenue | C4: Orders | D4: AOV | E4: Revenue Growth | F4: Status
A5: 46023 | B5: =SUMIFS('02_Clean_Data'!K5:K157,'02_Clean_Data'!B5:B157,">="&A5,'02_Clean_Data'!B5:B157,"<"&EDATE(A5,1)) | C5: =COUNTIFS('02_Clean_Data'!B5:B157,">="&A5,'02_Clean_Data'!B5:B157,"<"&EDATE(A5,1)) | D5: =IFERROR(B5/C5,0)
A6: 46054 | B6: =SUMIFS('02_Clean_Data'!K5:K157,'02_Clean_Data'!B5:B157,">="&A6,'02_Clean_Data'!B5:B157,"<"&EDATE(A6,1)) | C6: =COUNTIFS('02_Clean_Data'!B5:B157,">="&A6,'02_Clean_Data'!B5:B157,"<"&EDATE(A6,1)) | D6: =IFERROR(B6/C6,0) | E6: =IFERROR((B6-B5)/B5,0) | F6: =IF(E6>=0,"Growing","Declining")
A7: 46082 | B7: =SUMIFS('02_Clean_Data'!K5:K157,'02_Clean_Data'!B5:B157,">="&A7,'02_Clean_Data'!B5:B157,"<"&EDATE(A7,1)) | C7: =COUNTIFS('02_Clean_Data'!B5:B157,">="&A7,'02_Clean_Data'!B5:B157,"<"&EDATE(A7,1)) | D7: =IFERROR(B7/C7,0) | E7: =IFERROR((B7-B6)/B6,0) | F7: =IF(E7>=0,"Growing","Declining")
A8: 46113 | B8: =SUMIFS('02_Clean_Data'!K5:K157,'02_Clean_Data'!B5:B157,">="&A8,'02_Clean_Data'!B5:B157,"<"&EDATE(A8,1)) | C8: =COUNTIFS('02_Clean_Data'!B5:B157,">="&A8,'02_Clean_Data'!B5:B157,"<"&EDATE(A8,1)) | D8: =IFERROR(B8/C8,0) | E8: =IFERROR((B8-B7)/B7,0) | F8: =IF(E8>=0,"Growing","Declining")
A9: 46143 | B9: =SUMIFS('02_Clean_Data'!K5:K157,'02_Clean_Data'!B5:B157,">="&A9,'02_Clean_Data'!B5:B157,"<"&EDATE(A9,1)) | C9: =COUNTIFS('02_Clean_Data'!B5:B157,">="&A9,'02_Clean_Data'!B5:B157,"<"&EDATE(A9,1)) | D9: =IFERROR(B9/C9,0) | E9: =IFERROR((B9-B8)/B8,0) | F9: =IF(E9>=0,"Growing","Declining")
A10: 46174 | B10: =SUMIFS('02_Clean_Data'!K5:K157,'02_Clean_Data'!B5:B157,">="&A10,'02_Clean_Data'!B5:B157,"<"&EDATE(A10,1)) | C10: =COUNTIFS('02_Clean_Data'!B5:B157,">="&A10,'02_Clean_Data'!B5:B157,"<"&EDATE(A10,1)) | D10: =IFERROR(B10/C10,0) | E10: =IFERROR((B10-B9)/B9,0) | F10: =IF(E10>=0,"Growing","Declining")

Sheet 07_Interactive_Analysis
A1: Interactive Business Analysis
A2: Change the dropdown selections. KPI formulas update using SUMIFS / COUNTIFS.
A4: Selected Region | B4: West | D4: KPI | E4: Value
A5: Selected Category | B5: Electronics | D5: Filtered Revenue | E5: =SUMIFS('02_Clean_Data'!K5:K157,'02_Clean_Data'!F5:F157,B4,'02_Clean_Data'!D5:D157,B5,'02_Clean_Data'!G5:G157,B6)
A6: Selected Channel | B6: Online | D6: Filtered Orders | E6: =COUNTIFS('02_Clean_Data'!F5:F157,B4,'02_Clean_Data'!D5:D157,B5,'02_Clean_Data'!G5:G157,B6)
D7: Filtered AOV | E7: =IFERROR(E5/E6,0)
D8: High Revenue Orders | E8: =COUNTIFS('02_Clean_Data'!F5:F157,B4,'02_Clean_Data'!D5:D157,B5,'02_Clean_Data'!G5:G157,B6,'02_Clean_Data'!R5:R157,"High")
A9: Why this matters
A10: This sheet demonstrates Data Validation + SUMIFS + COUNTIFS + IFERROR. In an interview, explain that dropdowns change the criteria while the formulas recalculate the selected business segment.

Sheet 08_Executive_Dashboard
A1: AI BUSINESS ANALYST — EXECUTIVE DASHBOARD
A2: Management view built from the cleaned sales data. KPI cards + charts + business interpretation.
A4: Total Revenue | D4: Total Orders | G4: Average Order Value | J4: Top Product
A5: =SUM('02_Clean_Data'!K5:K157) | D5: =COUNTA('02_Clean_Data'!A5:A157) | G5: =AVERAGE('02_Clean_Data'!K5:K157) | J5: =INDEX('05_Pivot_Style'!A5:A12,MATCH(MAX('05_Pivot_Style'!B5:B12),'05_Pivot_Style'!B5:B12,0))
A9: Product Revenue | D9: Category Revenue | G9: Monthly Revenue
A10: Product | B10: Revenue | D10: Category | E10: Revenue | G10: Month | H10: Revenue
A11: ='05_Pivot_Style'!A5 | B11: ='05_Pivot_Style'!B5 | D11: ='05_Pivot_Style'!G5 | E11: ='05_Pivot_Style'!H5 | G11: ='06_Monthly_Analysis'!A5 | H11: ='06_Monthly_Analysis'!B5
A12: ='05_Pivot_Style'!A6 | B12: ='05_Pivot_Style'!B6 | D12: ='05_Pivot_Style'!G6 | E12: ='05_Pivot_Style'!H6 | G12: ='06_Monthly_Analysis'!A6 | H12: ='06_Monthly_Analysis'!B6
A13: ='05_Pivot_Style'!A7 | B13: ='05_Pivot_Style'!B7 | G13: ='06_Monthly_Analysis'!A7 | H13: ='06_Monthly_Analysis'!B7
A14: ='05_Pivot_Style'!A8 | B14: ='05_Pivot_Style'!B8 | G14: ='06_Monthly_Analysis'!A8 | H14: ='06_Monthly_Analysis'!B8
A15: ='05_Pivot_Style'!A9 | B15: ='05_Pivot_Style'!B9 | G15: ='06_Monthly_Analysis'!A9 | H15: ='06_Monthly_Analysis'!B9
A16: ='05_Pivot_Style'!A10 | B16: ='05_Pivot_Style'!B10 | G16: ='06_Monthly_Analysis'!A10 | H16: ='06_Monthly_Analysis'!B10
A17: ='05_Pivot_Style'!A11 | B17: ='05_Pivot_Style'!B11
A18: ='05_Pivot_Style'!A12 | B18: ='05_Pivot_Style'!B12

Sheet 09_Cleaning_Guide
A1: Data Cleaning Demonstration
A2: Shows what a real analyst would clean before reporting.
A4: Issue | B4: Example in Raw Data | C4: Cleaning Formula / Method | D4: Why it matters
A5: Extra spaces | B5: Laptop | C5: =PROPER(TRIM(cell)) | D5: Prevents mismatches in lookups and summaries
A6: Inconsistent case | B6: abc electronics | C6: =PROPER(TRIM(cell)) | D6: Standardizes labels
A7: Wrong / missing calculation | B7: Revenue | C7: =IFERROR(Quantity*Unit Price,0) | D7: Creates a reliable metric
A8: Duplicate records | B8: Repeated Order ID | C8: COUNTIF / Remove Duplicates | D8: Prevents double counting
A9: Date analysis | B9: 01-Jan-2026 | C9: YEAR / MONTH / EOMONTH | D9: Enables time-based analysis
A10: Missing lookup | B10: Unknown product | C10: IFERROR(XLOOKUP(...),"Not Found") | D10: Avoids formula errors

Sheet 10_Excel_Skills
A1: Excel Skills Demonstrated
A2: Use this page as a checklist when explaining the workbook in interviews.
A4: Skill | B4: Functions / Feature | C4: How it is used
A5: Data Cleaning | B5: TRIM, PROPER, IFERROR, duplicate awareness | C5: Standardized text and protected calculations from errors.
A6: Excel Tables | B6: Structured Tables + filters + freeze panes | C6: Makes raw data easier to manage and formulas scalable.
A7: Lookup Functions | B7: XLOOKUP, INDEX, MATCH | C7: Connects transactional data with reference/master data.
A8: Conditional Logic | B8: IF, IFS | C8: Creates revenue bands and business classifications.
A9: Conditional Aggregation | B9: SUMIF, SUMIFS, COUNTIF, COUNTIFS, AVERAGEIF | C9: Answers segment-specific business questions.
A10: Date Analysis | B10: YEAR, TEXT, EDATE | C10: Supports monthly trend reporting.
A11: Conditional Formatting | B11: Color scales and data bars | C11: Highlights strong/weak values quickly.
A12: Data Validation | B12: Dropdown selectors | C12: Creates interactive analysis without macros.
A13: Charts | B13: Bar, line, pie | C13: Communicates product, trend and category insights.
A14: Dashboarding | B14: KPI cards + charts | C14: Converts analysis into an executive-friendly view.
A15: Business Analysis | B15: Revenue, AOV, orders, margin | C15: Turns raw transactions into business KPIs.

Sheet 11_Data_Dictionary
A1: Data Dictionary
A2: Definitions of the main fields used in the business analysis.
A4: Field | B4: Definition | C4: Data Type
A5: Order ID | B5: Unique transaction identifier | C5: Integer
A6: Order Date | B6: Date of the transaction | C6: Date
A7: Product | B7: Product sold | C7: Text
A8: Category | B8: Product category | C8: Text
A9: Customer | B9: Customer / account name | C9: Text
A10: Region | B10: Sales region | C10: Text
A11: Channel | B11: Sales channel | C11: Text
A12: Salesperson | B12: Representative handling the transaction | C12: Text
A13: Quantity | B13: Units sold | C13: Integer
A14: Unit Price | B14: Price per unit | C14: Currency
A15: Revenue | B15: Quantity × Unit Price | C15: Currency
... A18: Revenue Band | B18: High / Medium / Low classification | C18: Text
